src/__init__.py
src/core/__init__.py
src/modules/__init__.py
src/modules/array_demo.py
src/modules/asyncio_demo.py
src/modules/atexit_demo.py
src/modules/bisect_demo.py
src/modules/code_demo.py
src/modules/collections_demo.py
src/modules/concurrent_futures_demo.py
src/modules/copy_demo.py
src/modules/functools_demo.py
src/modules/heapq_demo.py
src/modules/mmap_demo.py
src/modules/multiprocessing_demo.py
src/modules/pathlib_demo.py
src/modules/pickle_demo.py
src/modules/struct_demo.py
src/modules/subprocess_demo.py
src/modules/threading_demo.py
allezvamos-0.1.0.dist-info/METADATA
allezvamos-0.1.0.dist-info/WHEEL
allezvamos-0.1.0.dist-info/RECORD
